pinaxai/__init__.py
pinaxai/py.typed
pinaxai/aws/__init__.py
pinaxai/aws/api_client.py
pinaxai/aws/context.py
pinaxai/aws/resources.py
pinaxai/aws/app/__init__.py
pinaxai/aws/app/base.py
pinaxai/aws/app/celery/__init__.py
pinaxai/aws/app/celery/worker.py
pinaxai/aws/app/django/__init__.py
pinaxai/aws/app/django/django.py
pinaxai/aws/app/fastapi/__init__.py
pinaxai/aws/app/fastapi/fastapi.py
pinaxai/aws/app/streamlit/__init__.py
pinaxai/aws/app/streamlit/streamlit.py
pinaxai/aws/resource/__init__.py
pinaxai/aws/resource/base.py
pinaxai/aws/resource/reference.py
pinaxai/aws/resource/types.py
pinaxai/aws/resource/acm/__init__.py
pinaxai/aws/resource/acm/certificate.py
pinaxai/aws/resource/cloudformation/__init__.py
pinaxai/aws/resource/cloudformation/stack.py
pinaxai/aws/resource/ec2/__init__.py
pinaxai/aws/resource/ec2/security_group.py
pinaxai/aws/resource/ec2/subnet.py
pinaxai/aws/resource/ec2/volume.py
pinaxai/aws/resource/ecs/__init__.py
pinaxai/aws/resource/ecs/cluster.py
pinaxai/aws/resource/ecs/container.py
pinaxai/aws/resource/ecs/service.py
pinaxai/aws/resource/ecs/task_definition.py
pinaxai/aws/resource/ecs/volume.py
pinaxai/aws/resource/elasticache/__init__.py
pinaxai/aws/resource/elasticache/cluster.py
pinaxai/aws/resource/elasticache/subnet_group.py
pinaxai/aws/resource/elb/__init__.py
pinaxai/aws/resource/elb/listener.py
pinaxai/aws/resource/elb/load_balancer.py
pinaxai/aws/resource/elb/target_group.py
pinaxai/aws/resource/emr/__init__.py
pinaxai/aws/resource/emr/cluster.py
pinaxai/aws/resource/glue/__init__.py
pinaxai/aws/resource/glue/crawler.py
pinaxai/aws/resource/iam/__init__.py
pinaxai/aws/resource/iam/policy.py
pinaxai/aws/resource/iam/role.py
pinaxai/aws/resource/rds/__init__.py
pinaxai/aws/resource/rds/db_cluster.py
pinaxai/aws/resource/rds/db_instance.py
pinaxai/aws/resource/rds/db_subnet_group.py
pinaxai/aws/resource/s3/__init__.py
pinaxai/aws/resource/s3/bucket.py
pinaxai/aws/resource/s3/object.py
pinaxai/aws/resource/secret/__init__.py
pinaxai_aws-0.0.1.dist-info/METADATA
pinaxai_aws-0.0.1.dist-info/WHEEL
pinaxai_aws-0.0.1.dist-info/top_level.txt
pinaxai_aws-0.0.1.dist-info/RECORD
