Metadata-Version: 2.4
Name: pinaxai-aws
Version: 0.0.1
Summary: AWS resources for Pinaxai
Author-email: Greg Fitzgerald <Greg.Fitzgerald@pinax.tech>
Project-URL: homepage, https://pinax.tech
Project-URL: documentation, https://docs.pinax.tech
Requires-Python: >=3.7
Requires-Dist: boto3
Provides-Extra: dev
Requires-Dist: mypy; extra == "dev"
Requires-Dist: pytest; extra == "dev"
Requires-Dist: ruff; extra == "dev"
